dsa_cat_all/__init__.py
dsa_cat_all/eap.py
dsa_cat_all/language.json
dsa_cat_all/language_compiler.py
dsa_cat_all/lfc.py
dsa_cat_all/settings.json
dsa_cat_all/settings.py
dsa_cat_all/__pycache__/__init__.cpython-311.pyc
dsa_cat_all/__pycache__/eap.cpython-311.pyc
dsa_cat_all/__pycache__/language_compiler.cpython-311.pyc
dsa_cat_all/__pycache__/lfc.cpython-311.pyc
dsa_cat_all/__pycache__/settings.cpython-311.pyc
dsa_cat_all-0.1.1.0.dist-info/licenses/LICENSE
dsa_cat_all-0.1.1.0.dist-info/METADATA
dsa_cat_all-0.1.1.0.dist-info/WHEEL
dsa_cat_all-0.1.1.0.dist-info/top_level.txt
dsa_cat_all-0.1.1.0.dist-info/RECORD
