Metadata-Version: 2.4
Name: dsa_cat_all
Version: 0.1.1.0
Summary: Short description
Author: dsa_cat
License: Mozilla Public License Version 2.0
Requires-Python: >=3.8
License-File: LICENSE
Dynamic: license-file
